{"3435":{"user_number_view":{"number":"3435"},"user_card_view":{"avatar_url":"https://openseauserdata.com/files/bf583396bbc29777c2f2087717036061.png","display_name":"Tarun Sachdeva","username":"tarun","fid":"3435","bio":"Building https://aikido.work / Other experiments lab0324.xyz"},"num_casts_view":{"count":"9"},"num_likes_view":{"count":"19"},"topics_positive_view":{"entities":["community","juicebox"],"counts":["1","1"]},"topics_view":{"entities":["brands","bytecode","cast","cc0","community","episode","https://i.imgur.com/4xbuln6.jpg","https://i.imgur.com/guhn3px.jpg","https://i.imgur.com/jpyiu3g.jpg","@sinahab"],"counts":["1","1","1","1","1","1","1","1","1","1"]},"num_liked_by_view":{"count":"4"},"profile_fans_view":{"fans":[{"fid":417,"username":"northchop","display_name":"northchop","avatar_url":"https://i.imgur.com/AONaC8u.jpg","count":1},{"fid":2714,"username":"rhys","display_name":"rhys","avatar_url":"https://openseauserdata.com/files/f305e9084db398761fdddf441da69d22.svg","count":1},{"fid":3256,"username":"elizabeth","display_name":"elizabeth.ai","avatar_url":"https://i.seadn.io/gae/eTdjLl4UmDpSeGnk-bD8urb60GtanejAYnlw68XwNM8a52WxqE0ZPlUJgopkwB_eNAC04lb023UlSM_kuWso3cQqrDMWhKLC-nou?w=500&auto=format","count":1},{"fid":3435,"username":"tarun","display_name":"Tarun Sachdeva","avatar_url":"https://openseauserdata.com/files/bf583396bbc29777c2f2087717036061.png","count":1}]},"emojis_view":{"emojis":[]},"top_casts_view":{"top_casts":[{"text":"Is there a “producthunt for smart contracts”? I want somewhere where I can discover new protocols, learn about how they work, try them out in test/mainnets, and get their stats. A more focused Etherscan, in a sense.\n\nWould anyone be interested in this? If this cast gets any heat I’ll hack something together.","thread_hash":"0x7a318a3147db125828886c6c072cb631911268294acddd5448e58cc21a2b2bfb","hash":"0x7a318a3147db125828886c6c072cb631911268294acddd5448e58cc21a2b2bfb","likes":1,"replies":1,"recasts":0},{"text":"⌐◨-◨\n\n(coming soon) https://i.imgur.com/GUhN3px.jpg","thread_hash":"0x67d2e1006cc88f6f89f203f5f58983f586e7c5c1e80b493490fc1f1d63b06b6f","hash":"0x67d2e1006cc88f6f89f203f5f58983f586e7c5c1e80b493490fc1f1d63b06b6f","likes":1,"replies":0,"recasts":0},{"text":"gm purples","thread_hash":"0xc74fe96fa2c23aae7c893e49e12ff91afd7d54e90c0dc5f9980a4d53072eba09","hash":"0xc74fe96fa2c23aae7c893e49e12ff91afd7d54e90c0dc5f9980a4d53072eba09","likes":1,"replies":0,"recasts":0},{"text":"Playing with Stable Diffusion (via PlaygroundAI), using my avatar illustration as a reference image. This is way too much fun https://i.imgur.com/4XbuLN6.jpg","thread_hash":"0x69e859fd9170cf8351350e4abf10089bea5025e8bed40c9ff4df15b25e65cf4c","hash":"0x69e859fd9170cf8351350e4abf10089bea5025e8bed40c9ff4df15b25e65cf4c","likes":0,"replies":0,"recasts":0},{"text":"https://i.imgur.com/JpYIu3g.jpg","thread_hash":"0x6e3bd26a0efd9c71203f9014628c4ab6c463d2924dc54e11b35fec76c84f7060","hash":"0x6e3bd26a0efd9c71203f9014628c4ab6c463d2924dc54e11b35fec76c84f7060","likes":0,"replies":0,"recasts":0},{"text":"This episode of @sinahab’s Into the Bytecode pod ft. the Juicebox project is incredible - what an amazing community and mission: https://open.spotify.com/episode/0rjLMkFT6HgmHeXe4MuL8K","thread_hash":"0x1ebc9fea7703209bf8829bb96d251bf4a2e753b92ad580a0dc7ca4c5afb92596","hash":"0x1ebc9fea7703209bf8829bb96d251bf4a2e753b92ad580a0dc7ca4c5afb92596","likes":0,"replies":0,"recasts":0},{"text":"delete:farcaster://casts/0x13974adbc9ba29149cdc0f71cef8b77e3aa708c4296f031b9c3f3611ae88c305","thread_hash":"0x12c2f1b09af6a8be3c0b1498411288cc6995b8edd76a3de2f34b2a0faf377ced","hash":"0x12c2f1b09af6a8be3c0b1498411288cc6995b8edd76a3de2f34b2a0faf377ced","likes":0,"replies":0,"recasts":0},{"text":"What are some of the biggest CC0 brands in the web3 world? I know of Nouns, Toadz, Mfers, Punks(?)","thread_hash":"0x13974adbc9ba29149cdc0f71cef8b77e3aa708c4296f031b9c3f3611ae88c305","hash":"0x13974adbc9ba29149cdc0f71cef8b77e3aa708c4296f031b9c3f3611ae88c305","likes":0,"replies":0,"recasts":0}]},"first_cast_view":{"cast":{"fid":"3435","text":"gm purples","published_at":"2022-10-13T16:02:08.048Z","hash":"0xc74fe96fa2c23aae7c893e49e12ff91afd7d54e90c0dc5f9980a4d53072eba09"}},"top_domains_view":{"top_domains":[{"domain":"open.spotify.com","count":1}]},"responded_by_view":{"top_replies":[{"fid":3256,"username":"elizabeth","display_name":"elizabeth.ai","avatar_url":"https://i.seadn.io/gae/eTdjLl4UmDpSeGnk-bD8urb60GtanejAYnlw68XwNM8a52WxqE0ZPlUJgopkwB_eNAC04lb023UlSM_kuWso3cQqrDMWhKLC-nou?w=500&auto=format","count":1}]},"responded_to_view":{"top_replies":[]},"num_gms_view":{"count":"5"},"casts_over_time_view":{"data":[{"week":"2022-01-02T23:00:00.000Z","count":"0"},{"week":"2022-01-09T23:00:00.000Z","count":"0"},{"week":"2022-01-16T23:00:00.000Z","count":"0"},{"week":"2022-01-23T23:00:00.000Z","count":"0"},{"week":"2022-01-30T23:00:00.000Z","count":"0"},{"week":"2022-02-06T23:00:00.000Z","count":"0"},{"week":"2022-02-13T23:00:00.000Z","count":"0"},{"week":"2022-02-20T23:00:00.000Z","count":"0"},{"week":"2022-02-27T23:00:00.000Z","count":"0"},{"week":"2022-03-06T23:00:00.000Z","count":"0"},{"week":"2022-03-13T23:00:00.000Z","count":"0"},{"week":"2022-03-20T23:00:00.000Z","count":"0"},{"week":"2022-03-27T22:00:00.000Z","count":"0"},{"week":"2022-04-03T22:00:00.000Z","count":"0"},{"week":"2022-04-10T22:00:00.000Z","count":"0"},{"week":"2022-04-17T22:00:00.000Z","count":"0"},{"week":"2022-04-24T22:00:00.000Z","count":"0"},{"week":"2022-05-01T22:00:00.000Z","count":"0"},{"week":"2022-05-08T22:00:00.000Z","count":"0"},{"week":"2022-05-15T22:00:00.000Z","count":"0"},{"week":"2022-05-22T22:00:00.000Z","count":"0"},{"week":"2022-05-29T22:00:00.000Z","count":"0"},{"week":"2022-06-05T22:00:00.000Z","count":"0"},{"week":"2022-06-12T22:00:00.000Z","count":"0"},{"week":"2022-06-19T22:00:00.000Z","count":"0"},{"week":"2022-06-26T22:00:00.000Z","count":"0"},{"week":"2022-07-03T22:00:00.000Z","count":"0"},{"week":"2022-07-10T22:00:00.000Z","count":"0"},{"week":"2022-07-17T22:00:00.000Z","count":"0"},{"week":"2022-07-24T22:00:00.000Z","count":"0"},{"week":"2022-07-31T22:00:00.000Z","count":"0"},{"week":"2022-08-07T22:00:00.000Z","count":"0"},{"week":"2022-08-14T22:00:00.000Z","count":"0"},{"week":"2022-08-21T22:00:00.000Z","count":"0"},{"week":"2022-08-28T22:00:00.000Z","count":"0"},{"week":"2022-09-04T22:00:00.000Z","count":"0"},{"week":"2022-09-11T22:00:00.000Z","count":"0"},{"week":"2022-09-18T22:00:00.000Z","count":"0"},{"week":"2022-09-25T22:00:00.000Z","count":"0"},{"week":"2022-10-02T22:00:00.000Z","count":"0"},{"week":"2022-10-09T22:00:00.000Z","count":"1"},{"week":"2022-10-16T22:00:00.000Z","count":"1"},{"week":"2022-10-23T22:00:00.000Z","count":"2"},{"week":"2022-10-30T23:00:00.000Z","count":"0"},{"week":"2022-11-06T23:00:00.000Z","count":"1"},{"week":"2022-11-13T23:00:00.000Z","count":"0"},{"week":"2022-11-20T23:00:00.000Z","count":"4"},{"week":"2022-11-27T23:00:00.000Z","count":"0"},{"week":"2022-12-04T23:00:00.000Z","count":"0"},{"week":"2022-12-11T23:00:00.000Z","count":"0"},{"week":"2022-12-18T23:00:00.000Z","count":"0"}],"max":4},"casted_images_view":{"data":[{"url":"https://i.imgur.com/JpYIu3g.jpg","hash":"0x6e3bd26a0efd9c71203f9014628c4ab6c463d2924dc54e11b35fec76c84f7060"},{"url":"https://i.imgur.com/GUhN3px.jpg","hash":"0x67d2e1006cc88f6f89f203f5f58983f586e7c5c1e80b493490fc1f1d63b06b6f"},{"url":"https://i.imgur.com/4XbuLN6.jpg","hash":"0x69e859fd9170cf8351350e4abf10089bea5025e8bed40c9ff4df15b25e65cf4c"}]},"num_threads_view":{"count":0},"num_replies_view":{"count":0},"num_questions_view":{"count":"1"},"num_castaways_view":{"count":"3"},"personas_view":{"questioncaster":[0.1111111111111111,"1"],"lurkcaster":[0.020674646354733407,"19"],"ghostcaster":[0,"19",1672077571001.3318],"gramcaster":[0.3333333333333333,3],"replyguy":[0,0],"shillcaster":[0,0],"threadcastor":[0,0],"botcaster":[0,0],"castaway":[0.3333333333333333,"3"],"cryptocaster":[0,0],"birdappcaster":[0,0]}}}