{"150":{"user_number_view":{"number":"150"},"user_card_view":{"avatar_url":"https://lh3.googleusercontent.com/zmMvQRE1W1NFSHrgsbbLw4Yxc2CC4fJGszvkpfGywjWMSrNoc00LyWg2mHYGy1W7owYTJrtR0V6eq6Ggw1ePs50TMQ-o4bDHcAqn","display_name":"ⒿⒹⒽ","username":"jdh","fid":"150","bio":null},"num_casts_view":{"count":"6"},"num_likes_view":{"count":"1"},"topics_positive_view":{"entities":["crypto"],"counts":["1"]},"topics_view":{"entities":["twitter","crypto","he","his","https://i.imgur.com/vipxfec.png","instapaper","nikita","people","posts","tv"],"counts":["2","1","1","1","1","1","1","1","1","1"]},"num_liked_by_view":{"count":"20"},"profile_fans_view":{"fans":[{"fid":3,"username":"dwr","display_name":"Dan Romero","avatar_url":"https://res.cloudinary.com/merkle-manufactory/image/fetch/c_fill,f_png,w_256/https://lh3.googleusercontent.com/MyUBL0xHzMeBu7DXQAqv0bM9y6s4i4qjnhcXz5fxZKS3gwWgtamxxmxzCJX7m2cuYeGalyseCA2Y6OBKDMR06TWg2uwknnhdkDA1AA","count":5},{"fid":222,"username":"akashgarg","display_name":"akashgarg.eth","avatar_url":"https://lh3.googleusercontent.com/T9xCMIdSJnGjxrIlarGwd8BXfwJ_0d_qajNDm5r0utj6ByDiTCQ-8PemLiwjSwPWJBxqAG6v8z9l9yacDAY9Hf5_TEWeAuDR0WSPjQ","count":2},{"fid":16,"username":"zosegal","display_name":"Zach Segal","avatar_url":"https://github.com/zosegal.png","count":2},{"fid":129,"username":"phil","display_name":"phil","avatar_url":"https://i.seadn.io/gae/V0OzwojGHgQCB0BqJ-RkhmwFLuD847O-4lZ233f8zTlxbn-sWTI03Ue-RbB2tLlnRcNnB910AHGxZuxtISi5pRLsNIX1yU71E31p?w=500&auto=format","count":1},{"fid":130,"username":"stammy","display_name":"Stammy","avatar_url":"https://res.cloudinary.com/merkle-manufactory/image/fetch/c_fill,f_png,w_256/https://lh3.googleusercontent.com/Gs1uo-XR5iX6YNn9Egf1JgRCV8lg1id6uJdEZmDaWd4hspTXhRCQZtvT81o45yPRWIJwaKiT2P552bJQYv17zllUTJ1rMxntcj5g","count":1},{"fid":143,"username":"mk","display_name":"mk","avatar_url":"https://lh3.googleusercontent.com/VqX9ry1EZd6eFM-x1WYuut3UorMrHqE5zjyxLmpA15ItRgSJ80DcKEHeaVEfFCPg_mXeg7QhGYicCEr3Myq0TwhfZNtjTS47lvTrhV0","count":1},{"fid":251,"username":"jc","display_name":"jcdenton.eth","avatar_url":"https://i.seadn.io/gae/YhxEbbtny4UArVsekY3Qxn0fvFmoc6EcLr01TN2ZhTIxvDLpvw3W8rX_S6XUZFZBq7rfNJtZDOcY8J65f-LiD3F5ojLAZHrLx9QF-A?w=500&auto=format","count":1},{"fid":260,"username":"yekim","display_name":"Mike","avatar_url":"https://i.seadn.io/gae/UycAYeUABliMcNctJMFmA3yH2oOKTmgwv6FWjd28kB5sbAcbtlJ8bQGLp_CpW5KLB3X03oxippSVIYCDBVuBz4-jnAuurAibpt-D?w=500&auto=format","count":1},{"fid":279,"username":"trulovenyc","display_name":"Trupti","avatar_url":"https://lh3.googleusercontent.com/muN6el_M3-TI-9yesuV5BrpaL6Gnt5hlo4X44d2JKfqdLV3Z8Kv3m0NTEkoofK-hl3AGNgt-3vQzVfNGr6RRoA7d8ztmDYsg7OpLqA","count":1},{"fid":370,"username":"coravos","display_name":"Andy Coravos","avatar_url":"https://lh3.googleusercontent.com/TW9rS2v6AYosLi7kJ0Oa7v_P1XMk72KtPs0P1CBh_L1DGOwU8RSoO0PJXVNN6RfgqACZZiLmS-XtjZ0B8tOkpKZ5-RZfcsl0ls4vvQ","count":1}]},"emojis_view":{"emojis":[]},"top_casts_view":{"top_casts":[{"text":"Youtube TV","thread_hash":null,"hash":"0x9face28302825ad25c008d775b5eeab81de09da7f1188cac7a92c8bd8b133884","likes":5,"replies":0,"recasts":0},{"text":"Nikita really just uses twitter to try to hack twitter into engagement. Look through all his posts, it's all about polarizing people to drive sharing and engagement, I wouldn't take anything he says as a goal of sharing knowledge, just sparking emotion","thread_hash":null,"hash":"0x27198270ba1f0aa557c523103583f8fad86437dd36bc16e800b994943deaf70e","likes":4,"replies":1,"recasts":0},{"text":"See: https://i.imgur.com/VIpxFEC.png","thread_hash":null,"hash":"0x4eb157de068c7e1a616f6f0a5e18545ea13eec65418b2f581fd9f2519634c1a3","likes":4,"replies":0,"recasts":0},{"text":"Thanks!!","thread_hash":"0x72a725234713d51c8a5c2d1e0aa15fdc49a3ae64b16252292ed69f450f8ec99a","hash":"0x907d51a3e4d0f0d336652b8cc5c1e9ae303002f61d78063c0b0b99f338d12c45","likes":3,"replies":0,"recasts":0},{"text":"Wire transfer feels so outdated once you get used to crypto","thread_hash":null,"hash":"0x8f1f0dd1b4dd16c4a700ba24de92da9f53c9dbd3c1d0ff60a14509b491ec2c21","likes":2,"replies":0,"recasts":0},{"text":"The new instapaper","thread_hash":null,"hash":"0xc91a9bf1f2705186fc72a6d4eb14703a505b26880732021bd6227281e128115e","likes":2,"replies":0,"recasts":0}]},"first_cast_view":{"cast":null},"top_domains_view":{"top_domains":[]},"responded_by_view":{"top_replies":[]},"responded_to_view":{"top_replies":[{"fid":129,"username":"phil","display_name":"phil","avatar_url":"https://i.seadn.io/gae/V0OzwojGHgQCB0BqJ-RkhmwFLuD847O-4lZ233f8zTlxbn-sWTI03Ue-RbB2tLlnRcNnB910AHGxZuxtISi5pRLsNIX1yU71E31p?w=500&auto=format","count":1}]},"num_gms_view":{"count":0},"casts_over_time_view":{"data":[{"week":"2022-01-02T23:00:00.000Z","count":"3"},{"week":"2022-01-09T23:00:00.000Z","count":"0"},{"week":"2022-01-16T23:00:00.000Z","count":"0"},{"week":"2022-01-23T23:00:00.000Z","count":"0"},{"week":"2022-01-30T23:00:00.000Z","count":"0"},{"week":"2022-02-06T23:00:00.000Z","count":"0"},{"week":"2022-02-13T23:00:00.000Z","count":"0"},{"week":"2022-02-20T23:00:00.000Z","count":"0"},{"week":"2022-02-27T23:00:00.000Z","count":"0"},{"week":"2022-03-06T23:00:00.000Z","count":"0"},{"week":"2022-03-13T23:00:00.000Z","count":"2"},{"week":"2022-03-20T23:00:00.000Z","count":"0"},{"week":"2022-03-27T22:00:00.000Z","count":"0"},{"week":"2022-04-03T22:00:00.000Z","count":"0"},{"week":"2022-04-10T22:00:00.000Z","count":"0"},{"week":"2022-04-17T22:00:00.000Z","count":"0"},{"week":"2022-04-24T22:00:00.000Z","count":"0"},{"week":"2022-05-01T22:00:00.000Z","count":"0"},{"week":"2022-05-08T22:00:00.000Z","count":"0"},{"week":"2022-05-15T22:00:00.000Z","count":"0"},{"week":"2022-05-22T22:00:00.000Z","count":"0"},{"week":"2022-05-29T22:00:00.000Z","count":"1"},{"week":"2022-06-05T22:00:00.000Z","count":"0"},{"week":"2022-06-12T22:00:00.000Z","count":"0"},{"week":"2022-06-19T22:00:00.000Z","count":"0"},{"week":"2022-06-26T22:00:00.000Z","count":"0"},{"week":"2022-07-03T22:00:00.000Z","count":"0"},{"week":"2022-07-10T22:00:00.000Z","count":"0"},{"week":"2022-07-17T22:00:00.000Z","count":"0"},{"week":"2022-07-24T22:00:00.000Z","count":"0"},{"week":"2022-07-31T22:00:00.000Z","count":"0"},{"week":"2022-08-07T22:00:00.000Z","count":"0"},{"week":"2022-08-14T22:00:00.000Z","count":"0"},{"week":"2022-08-21T22:00:00.000Z","count":"0"},{"week":"2022-08-28T22:00:00.000Z","count":"0"},{"week":"2022-09-04T22:00:00.000Z","count":"0"},{"week":"2022-09-11T22:00:00.000Z","count":"0"},{"week":"2022-09-18T22:00:00.000Z","count":"0"},{"week":"2022-09-25T22:00:00.000Z","count":"0"},{"week":"2022-10-02T22:00:00.000Z","count":"0"},{"week":"2022-10-09T22:00:00.000Z","count":"0"},{"week":"2022-10-16T22:00:00.000Z","count":"0"},{"week":"2022-10-23T22:00:00.000Z","count":"0"},{"week":"2022-10-30T23:00:00.000Z","count":"0"},{"week":"2022-11-06T23:00:00.000Z","count":"0"},{"week":"2022-11-13T23:00:00.000Z","count":"0"},{"week":"2022-11-20T23:00:00.000Z","count":"0"},{"week":"2022-11-27T23:00:00.000Z","count":"0"},{"week":"2022-12-04T23:00:00.000Z","count":"0"},{"week":"2022-12-11T23:00:00.000Z","count":"0"},{"week":"2022-12-18T23:00:00.000Z","count":"0"}],"max":3},"casted_images_view":{"data":[{"url":"https://i.imgur.com/VIpxFEC.png","hash":"0x4eb157de068c7e1a616f6f0a5e18545ea13eec65418b2f581fd9f2519634c1a3"}]},"num_threads_view":{"count":0},"num_replies_view":{"count":"6"},"num_questions_view":{"count":0},"num_castaways_view":{"count":0},"personas_view":{"questioncaster":[0,0],"lurkcaster":[0.01639344262295082,"1"],"ghostcaster":[0.84,"1",null],"gramcaster":[0.16666666666666666,1],"replyguy":[1,"6"],"shillcaster":[0,0],"threadcastor":[0,0],"botcaster":[0.375,"6"],"castaway":[0,0],"cryptocaster":[0.16666666666666666,"01"],"birdappcaster":[0,0]}}}