{"3108":{"user_number_view":{"number":"3108"},"user_card_view":{"avatar_url":"https://i.imgur.com/rCief5P.jpg","display_name":"ujjwal nadhani","username":"ujjwal","fid":"3108","bio":null},"num_casts_view":{"count":"6"},"num_likes_view":{"count":"12"},"topics_positive_view":{"entities":["niemann","weekend"],"counts":["1","1"]},"topics_view":{"entities":["entities","niemann","the","weekend"],"counts":["1","1","1","1","1","1","1"]},"num_liked_by_view":{"count":"1"},"profile_fans_view":{"fans":[{"fid":2768,"username":"thejuice","display_name":"nancy","avatar_url":"https://lh3.googleusercontent.com/QWIz5VrfrsfO8lyIvigTanq8FGvTt4bs4y9iTPnMOHggCzMR_twG-AAU3BkTuZ4SKa8D-tLLbo9vRuV0AyuCgoxuBkoYdG1CgVTt","count":1}]},"emojis_view":{"emojis":[]},"top_casts_view":{"top_casts":[{"text":"Niemann’s lawsuit against the biggest entities in chess feels eerily representative of the overall fight against centralized monopolies","thread_hash":"0x3e7776823481fbe00e918944961075fc2a6dcd0a88a9cd14e23173cb7e2c01cd","hash":"0x3e7776823481fbe00e918944961075fc2a6dcd0a88a9cd14e23173cb7e2c01cd","likes":1,"replies":0,"recasts":0},{"text":"wing it - best part about the weekend is you can do whatever you feel like","thread_hash":"0x5344e726d15af9022ba26b2f04273dafb1835bf02f6931008b20214a1b6c2803","hash":"0xddfd05b1cda34769deb5ac2f24b5e6a79b8c2cd59622c80c13ce8ee0f5c0f71c","likes":0,"replies":0,"recasts":0},{"text":"necessary for my mental health and sanity","thread_hash":"0x492b3d5353e13c397244f4e78aeb6c7cc625eb041adc39c8f59d2deba189ffd7","hash":"0x0b43e11a976755f8cc98eef1b8e6c838af619021db688350811a96d88a20b3b2","likes":0,"replies":0,"recasts":0}]},"first_cast_view":{"cast":{"fid":"3108","text":"Niemann’s lawsuit against the biggest entities in chess feels eerily representative of the overall fight against centralized monopolies","published_at":"2022-10-20T22:28:18.557Z","hash":"0x3e7776823481fbe00e918944961075fc2a6dcd0a88a9cd14e23173cb7e2c01cd"}},"top_domains_view":{"top_domains":[]},"responded_by_view":{"top_replies":[]},"responded_to_view":{"top_replies":[{"fid":127,"username":"neuroswish","display_name":"Kiran","avatar_url":"https://pbs.twimg.com/profile_images/1572434339790557185/pGy6n8b4_400x400.jpg","count":1},{"fid":3492,"username":"willc","display_name":"will collier","avatar_url":"https://i.seadn.io/gae/jqTbqYydL4mKNkh4hZmyrJ0948qhPySELLbZuuA87nTSuV5Defmv39SzdDsBUj4qYLrUnof7qqbBDbjczWP2Ko8CIAziQs5F4VOzB88?w=500&auto=format","count":1}]},"num_gms_view":{"count":0},"casts_over_time_view":{"data":[{"week":"2022-01-02T23:00:00.000Z","count":"0"},{"week":"2022-01-09T23:00:00.000Z","count":"0"},{"week":"2022-01-16T23:00:00.000Z","count":"0"},{"week":"2022-01-23T23:00:00.000Z","count":"0"},{"week":"2022-01-30T23:00:00.000Z","count":"0"},{"week":"2022-02-06T23:00:00.000Z","count":"0"},{"week":"2022-02-13T23:00:00.000Z","count":"0"},{"week":"2022-02-20T23:00:00.000Z","count":"0"},{"week":"2022-02-27T23:00:00.000Z","count":"0"},{"week":"2022-03-06T23:00:00.000Z","count":"0"},{"week":"2022-03-13T23:00:00.000Z","count":"0"},{"week":"2022-03-20T23:00:00.000Z","count":"0"},{"week":"2022-03-27T22:00:00.000Z","count":"0"},{"week":"2022-04-03T22:00:00.000Z","count":"0"},{"week":"2022-04-10T22:00:00.000Z","count":"0"},{"week":"2022-04-17T22:00:00.000Z","count":"0"},{"week":"2022-04-24T22:00:00.000Z","count":"0"},{"week":"2022-05-01T22:00:00.000Z","count":"0"},{"week":"2022-05-08T22:00:00.000Z","count":"0"},{"week":"2022-05-15T22:00:00.000Z","count":"0"},{"week":"2022-05-22T22:00:00.000Z","count":"0"},{"week":"2022-05-29T22:00:00.000Z","count":"0"},{"week":"2022-06-05T22:00:00.000Z","count":"0"},{"week":"2022-06-12T22:00:00.000Z","count":"0"},{"week":"2022-06-19T22:00:00.000Z","count":"0"},{"week":"2022-06-26T22:00:00.000Z","count":"0"},{"week":"2022-07-03T22:00:00.000Z","count":"0"},{"week":"2022-07-10T22:00:00.000Z","count":"0"},{"week":"2022-07-17T22:00:00.000Z","count":"0"},{"week":"2022-07-24T22:00:00.000Z","count":"0"},{"week":"2022-07-31T22:00:00.000Z","count":"0"},{"week":"2022-08-07T22:00:00.000Z","count":"0"},{"week":"2022-08-14T22:00:00.000Z","count":"0"},{"week":"2022-08-21T22:00:00.000Z","count":"0"},{"week":"2022-08-28T22:00:00.000Z","count":"0"},{"week":"2022-09-04T22:00:00.000Z","count":"0"},{"week":"2022-09-11T22:00:00.000Z","count":"0"},{"week":"2022-09-18T22:00:00.000Z","count":"0"},{"week":"2022-09-25T22:00:00.000Z","count":"0"},{"week":"2022-10-02T22:00:00.000Z","count":"0"},{"week":"2022-10-09T22:00:00.000Z","count":"3"},{"week":"2022-10-16T22:00:00.000Z","count":"3"},{"week":"2022-10-23T22:00:00.000Z","count":"0"},{"week":"2022-10-30T23:00:00.000Z","count":"0"},{"week":"2022-11-06T23:00:00.000Z","count":"0"},{"week":"2022-11-13T23:00:00.000Z","count":"0"},{"week":"2022-11-20T23:00:00.000Z","count":"0"},{"week":"2022-11-27T23:00:00.000Z","count":"0"},{"week":"2022-12-04T23:00:00.000Z","count":"0"},{"week":"2022-12-11T23:00:00.000Z","count":"0"},{"week":"2022-12-18T23:00:00.000Z","count":"0"}],"max":3},"casted_images_view":{"data":[]},"num_threads_view":{"count":0},"num_replies_view":{"count":"2"},"num_questions_view":{"count":0},"num_castaways_view":{"count":0},"personas_view":{"questioncaster":[0,0],"lurkcaster":[0.0196078431372549,"12"],"ghostcaster":[0,"12",1672076313961.0637],"gramcaster":[0,0],"replyguy":[0.3333333333333333,"2"],"shillcaster":[0,0],"threadcastor":[0,0],"botcaster":[0.015873015873015872,"2"],"castaway":[0,0],"cryptocaster":[0,0],"birdappcaster":[0,0]}}}