{"3052":{"user_number_view":{"number":"3052"},"user_card_view":{"avatar_url":"https://explorer.farcaster.xyz/avatar.png","display_name":"bhoga.eth","username":"bhoga","fid":"3052","bio":"web3 nerd"},"num_casts_view":{"count":"1"},"num_likes_view":{"count":"0"},"topics_positive_view":{"entities":[],"counts":[]},"topics_view":{"entities":["hello world","https://i.imgur.com/xtuqf3v.jpg"],"counts":["1","1"]},"num_liked_by_view":{"count":"5"},"profile_fans_view":{"fans":[{"fid":124,"username":"giu","display_name":"Giuliano Giacaglia","avatar_url":"https://res.cloudinary.com/merkle-manufactory/image/fetch/c_fill,f_png,w_256/https://lh3.googleusercontent.com/5IBmao06AhDg3PqXjNi1vm6D-HXDGXtkK8qk9vASUqGuJ4AHo2_p23QmyREZJjfzD9MzzAaHSOE2MWGIAwXGZjYnmTwvaDyz57As","count":1},{"fid":474,"username":"pdr","display_name":"Peter Rood","avatar_url":"https://i.seadn.io/gae/F-g4Y0OlaDZmK2m-rzPvN2hX1Vx2seHmxCSFwj7rrysVjcsHeSsNwpInQgg_KOf5MxzEECF6pci87d5JZ2mp1gPjxhCtPQLt6NiILg?w=500&auto=format","count":1},{"fid":689,"username":"kiyo","display_name":"Kiyo 🥷☕️","avatar_url":"https://lh3.googleusercontent.com/d6aU4ANXiRE3S1NOHTWbAqa0MDKYWsWgY8nJVTC-sSM77ke5B3bbHyAM3NfhBDpzdQUML5R0KRNh8dAk4iSzUen8HFBKa0R1LtUtOg","count":1},{"fid":1230,"username":"abc","display_name":"abc","avatar_url":"https://lh3.googleusercontent.com/c3WCdzqT5PVKSqzk2813_tjao3VAOA5qvhnYvWS5GwBVHA5nJCMEFzSk7QpsZY3mUvDiRGGt_b1KjO3Pq_DHs-52SjNZJUVcmiI-Gh4","count":1},{"fid":1946,"username":"dragonbanec","display_name":"Dragonbane Creation","avatar_url":"https://i.seadn.io/gae/PVTEgTvNCn205Ipl_aAEZE5BWXU_zTp-Mg7iJDbjnjHWXIzmvzJTHGnKGTukirlWMpcW-eu6U5tUIrg0pFu21EEkVetuCGBo2-l_Ky0?w=500&auto=format","count":1}]},"emojis_view":{"emojis":[]},"top_casts_view":{"top_casts":[{"text":"Hello World!\n https://i.imgur.com/xtUQF3V.jpg","thread_hash":"0xa083707f87683bb96c6eae407c90ef8030f9f099c335cdca4e1d99e08b8a3757","hash":"0xa083707f87683bb96c6eae407c90ef8030f9f099c335cdca4e1d99e08b8a3757","likes":5,"replies":0,"recasts":1}]},"first_cast_view":{"cast":{"fid":"3052","text":"Hello World!\n https://i.imgur.com/xtUQF3V.jpg","published_at":"2022-10-10T17:59:52.507Z","hash":"0xa083707f87683bb96c6eae407c90ef8030f9f099c335cdca4e1d99e08b8a3757"}},"top_domains_view":{"top_domains":[]},"responded_by_view":{"top_replies":[]},"responded_to_view":{"top_replies":[]},"num_gms_view":{"count":0},"casts_over_time_view":{"data":[{"week":"2022-01-02T23:00:00.000Z","count":"0"},{"week":"2022-01-09T23:00:00.000Z","count":"0"},{"week":"2022-01-16T23:00:00.000Z","count":"0"},{"week":"2022-01-23T23:00:00.000Z","count":"0"},{"week":"2022-01-30T23:00:00.000Z","count":"0"},{"week":"2022-02-06T23:00:00.000Z","count":"0"},{"week":"2022-02-13T23:00:00.000Z","count":"0"},{"week":"2022-02-20T23:00:00.000Z","count":"0"},{"week":"2022-02-27T23:00:00.000Z","count":"0"},{"week":"2022-03-06T23:00:00.000Z","count":"0"},{"week":"2022-03-13T23:00:00.000Z","count":"0"},{"week":"2022-03-20T23:00:00.000Z","count":"0"},{"week":"2022-03-27T22:00:00.000Z","count":"0"},{"week":"2022-04-03T22:00:00.000Z","count":"0"},{"week":"2022-04-10T22:00:00.000Z","count":"0"},{"week":"2022-04-17T22:00:00.000Z","count":"0"},{"week":"2022-04-24T22:00:00.000Z","count":"0"},{"week":"2022-05-01T22:00:00.000Z","count":"0"},{"week":"2022-05-08T22:00:00.000Z","count":"0"},{"week":"2022-05-15T22:00:00.000Z","count":"0"},{"week":"2022-05-22T22:00:00.000Z","count":"0"},{"week":"2022-05-29T22:00:00.000Z","count":"0"},{"week":"2022-06-05T22:00:00.000Z","count":"0"},{"week":"2022-06-12T22:00:00.000Z","count":"0"},{"week":"2022-06-19T22:00:00.000Z","count":"0"},{"week":"2022-06-26T22:00:00.000Z","count":"0"},{"week":"2022-07-03T22:00:00.000Z","count":"0"},{"week":"2022-07-10T22:00:00.000Z","count":"0"},{"week":"2022-07-17T22:00:00.000Z","count":"0"},{"week":"2022-07-24T22:00:00.000Z","count":"0"},{"week":"2022-07-31T22:00:00.000Z","count":"0"},{"week":"2022-08-07T22:00:00.000Z","count":"0"},{"week":"2022-08-14T22:00:00.000Z","count":"0"},{"week":"2022-08-21T22:00:00.000Z","count":"0"},{"week":"2022-08-28T22:00:00.000Z","count":"0"},{"week":"2022-09-04T22:00:00.000Z","count":"0"},{"week":"2022-09-11T22:00:00.000Z","count":"0"},{"week":"2022-09-18T22:00:00.000Z","count":"0"},{"week":"2022-09-25T22:00:00.000Z","count":"0"},{"week":"2022-10-02T22:00:00.000Z","count":"0"},{"week":"2022-10-09T22:00:00.000Z","count":"1"},{"week":"2022-10-16T22:00:00.000Z","count":"0"},{"week":"2022-10-23T22:00:00.000Z","count":"0"},{"week":"2022-10-30T23:00:00.000Z","count":"0"},{"week":"2022-11-06T23:00:00.000Z","count":"0"},{"week":"2022-11-13T23:00:00.000Z","count":"0"},{"week":"2022-11-20T23:00:00.000Z","count":"0"},{"week":"2022-11-27T23:00:00.000Z","count":"0"},{"week":"2022-12-04T23:00:00.000Z","count":"0"},{"week":"2022-12-11T23:00:00.000Z","count":"0"},{"week":"2022-12-18T23:00:00.000Z","count":"0"}],"max":1},"casted_images_view":{"data":[{"url":"https://i.imgur.com/xtUQF3V.jpg","hash":"0xa083707f87683bb96c6eae407c90ef8030f9f099c335cdca4e1d99e08b8a3757"}]},"num_threads_view":{"count":0},"num_replies_view":{"count":0},"num_questions_view":{"count":0},"num_castaways_view":{"count":0},"personas_view":{"questioncaster":[0,0],"lurkcaster":[0,"0"],"ghostcaster":[0.99,"0",1672076085605.25],"gramcaster":[1,1],"replyguy":[0,0],"shillcaster":[0,0],"threadcastor":[0,0],"botcaster":[0,0],"castaway":[0,0],"cryptocaster":[0,0],"birdappcaster":[0,0]}}}