{"664":{"user_number_view":{"number":"664"},"user_card_view":{"avatar_url":"https://lh3.googleusercontent.com/k5w2i9RVaM6-xwC-9IAFhtlIx6YD7d5W0NBy70c8Zu58OWIS5fWXEvcy-3-TanguXOjRtjGwTfPqYpx4-mA7WgHb5ISSbx5fl5j4Uw","display_name":"cola","username":"cola","fid":"664","bio":"I’m a balancer "},"num_casts_view":{"count":"3"},"num_likes_view":{"count":"4"},"topics_positive_view":{"entities":[],"counts":[]},"topics_view":{"entities":["mev","wagmi"],"counts":["1","1"]},"num_liked_by_view":{"count":"15"},"profile_fans_view":{"fans":[{"fid":474,"username":"pdr","display_name":"Peter Rood","avatar_url":"https://i.seadn.io/gae/F-g4Y0OlaDZmK2m-rzPvN2hX1Vx2seHmxCSFwj7rrysVjcsHeSsNwpInQgg_KOf5MxzEECF6pci87d5JZ2mp1gPjxhCtPQLt6NiILg?w=500&auto=format","count":2},{"fid":664,"username":"cola","display_name":"cola","avatar_url":"https://lh3.googleusercontent.com/k5w2i9RVaM6-xwC-9IAFhtlIx6YD7d5W0NBy70c8Zu58OWIS5fWXEvcy-3-TanguXOjRtjGwTfPqYpx4-mA7WgHb5ISSbx5fl5j4Uw","count":2},{"fid":1083,"username":"datz","display_name":"Datz | DeStore ","avatar_url":"https://i.seadn.io/gae/lHGrlUJdVzFvHv_f-0NF_8DjcJLW4LSAjjTuxO3XlZ63dOesr7mJTiwqNfDXzXWJQAQCHrDxP7JilcIVFN_flv0PfX1cPT4m5CkduQ?w=500&auto=format","count":2},{"fid":1287,"username":"july","display_name":"July","avatar_url":"https://i.imgur.com/dkogN90.jpg","count":2},{"fid":1626,"username":"mcbain","display_name":"Graham McBain","avatar_url":"https://lh3.googleusercontent.com/ux65IIYjKQ84rYldEQWGj1zZQ0WqDBPA-mP6ueGtMcoKA-w21-vpdZtv_vNT8M6eudW3BEdIa3eSJxAbwyJchQVszTvX0OHu_UlsP38","count":1},{"fid":1655,"username":"juan","display_name":"Juan Rivera Perez","avatar_url":"https://i.imgur.com/13ATfIj.jpg","count":1},{"fid":274,"username":"n","display_name":"Nico","avatar_url":"https://lh3.googleusercontent.com/EYngmyheqv2rtcwSkpvHavxCrkh9G9vlN1llhZaxoJoIThnPOg_dseMCFtcL35K9YG3644cJzYt1Ov1BhTSUiPmpDcgB1Zi9VodouA","count":1},{"fid":2275,"username":"hambone","display_name":"Hambone (0xhambone.eth)","avatar_url":"https://i.imgur.com/slpWCHP.jpg","count":1},{"fid":528,"username":"0xen","display_name":"0xen","avatar_url":"https://i.seadn.io/gae/22xIROA8S2jCU0uDBvUGIHp6Fk5cTl66-u_MVfxroP7hYMy-9psPEIbRQDC5q0m8PxCkLNMSxSdkyWe7yzB_sJQ8j8kV8Ao_R2oV?w=500&auto=format","count":1},{"fid":617,"username":"cameron","display_name":"Cameron Armstrong","avatar_url":"https://res.cloudinary.com/merkle-manufactory/image/fetch/c_fill,f_png,w_256/https://lh3.googleusercontent.com/2DuTQOaL5nJjMrA1tmfo8rjMwt7_0d04uj8nZgPnsEfpFsyNQh_s8qVDZHrpztpTCV67EvAE9b95zJYa1fRdjOpr-KeIAPGhoztP","count":1}]},"emojis_view":{"emojis":[]},"top_casts_view":{"top_casts":[{"text":"Gm","thread_hash":"0x29de2193e84b3a890437b55db7f0c085a84ee3a4f243ce9ddf6f5d980a42f999","hash":"0x29de2193e84b3a890437b55db7f0c085a84ee3a4f243ce9ddf6f5d980a42f999","likes":6,"replies":1,"recasts":0},{"text":"what about mev?","thread_hash":"0x6eec416242764479a7f0157ccfacf0899b5625d8c60c82420a587490862156a0","hash":"0x6eec416242764479a7f0157ccfacf0899b5625d8c60c82420a587490862156a0","likes":6,"replies":0,"recasts":0},{"text":"Wagmi","thread_hash":"0x514374541abadab3050ab500824a5244e5b0acb37f52cbd592d6b7fd55be4da5","hash":"0x514374541abadab3050ab500824a5244e5b0acb37f52cbd592d6b7fd55be4da5","likes":3,"replies":0,"recasts":0}]},"first_cast_view":{"cast":{"fid":"664","text":"Gm","published_at":"2022-06-04T04:20:37.783Z","hash":"0x29de2193e84b3a890437b55db7f0c085a84ee3a4f243ce9ddf6f5d980a42f999"}},"top_domains_view":{"top_domains":[]},"responded_by_view":{"top_replies":[{"fid":1655,"username":"juan","display_name":"Juan Rivera Perez","avatar_url":"https://i.imgur.com/13ATfIj.jpg","count":1}]},"responded_to_view":{"top_replies":[]},"num_gms_view":{"count":"1"},"casts_over_time_view":{"data":[{"week":"2022-01-02T23:00:00.000Z","count":"0"},{"week":"2022-01-09T23:00:00.000Z","count":"0"},{"week":"2022-01-16T23:00:00.000Z","count":"0"},{"week":"2022-01-23T23:00:00.000Z","count":"0"},{"week":"2022-01-30T23:00:00.000Z","count":"0"},{"week":"2022-02-06T23:00:00.000Z","count":"0"},{"week":"2022-02-13T23:00:00.000Z","count":"0"},{"week":"2022-02-20T23:00:00.000Z","count":"0"},{"week":"2022-02-27T23:00:00.000Z","count":"0"},{"week":"2022-03-06T23:00:00.000Z","count":"0"},{"week":"2022-03-13T23:00:00.000Z","count":"0"},{"week":"2022-03-20T23:00:00.000Z","count":"0"},{"week":"2022-03-27T22:00:00.000Z","count":"0"},{"week":"2022-04-03T22:00:00.000Z","count":"0"},{"week":"2022-04-10T22:00:00.000Z","count":"0"},{"week":"2022-04-17T22:00:00.000Z","count":"0"},{"week":"2022-04-24T22:00:00.000Z","count":"0"},{"week":"2022-05-01T22:00:00.000Z","count":"0"},{"week":"2022-05-08T22:00:00.000Z","count":"0"},{"week":"2022-05-15T22:00:00.000Z","count":"0"},{"week":"2022-05-22T22:00:00.000Z","count":"0"},{"week":"2022-05-29T22:00:00.000Z","count":"2"},{"week":"2022-06-05T22:00:00.000Z","count":"0"},{"week":"2022-06-12T22:00:00.000Z","count":"0"},{"week":"2022-06-19T22:00:00.000Z","count":"0"},{"week":"2022-06-26T22:00:00.000Z","count":"0"},{"week":"2022-07-03T22:00:00.000Z","count":"0"},{"week":"2022-07-10T22:00:00.000Z","count":"0"},{"week":"2022-07-17T22:00:00.000Z","count":"0"},{"week":"2022-07-24T22:00:00.000Z","count":"0"},{"week":"2022-07-31T22:00:00.000Z","count":"0"},{"week":"2022-08-07T22:00:00.000Z","count":"0"},{"week":"2022-08-14T22:00:00.000Z","count":"0"},{"week":"2022-08-21T22:00:00.000Z","count":"0"},{"week":"2022-08-28T22:00:00.000Z","count":"0"},{"week":"2022-09-04T22:00:00.000Z","count":"1"},{"week":"2022-09-11T22:00:00.000Z","count":"0"},{"week":"2022-09-18T22:00:00.000Z","count":"0"},{"week":"2022-09-25T22:00:00.000Z","count":"0"},{"week":"2022-10-02T22:00:00.000Z","count":"0"},{"week":"2022-10-09T22:00:00.000Z","count":"0"},{"week":"2022-10-16T22:00:00.000Z","count":"0"},{"week":"2022-10-23T22:00:00.000Z","count":"0"},{"week":"2022-10-30T23:00:00.000Z","count":"0"},{"week":"2022-11-06T23:00:00.000Z","count":"0"},{"week":"2022-11-13T23:00:00.000Z","count":"0"},{"week":"2022-11-20T23:00:00.000Z","count":"0"},{"week":"2022-11-27T23:00:00.000Z","count":"0"},{"week":"2022-12-04T23:00:00.000Z","count":"0"},{"week":"2022-12-11T23:00:00.000Z","count":"0"},{"week":"2022-12-18T23:00:00.000Z","count":"0"}],"max":2},"casted_images_view":{"data":[]},"num_threads_view":{"count":0},"num_replies_view":{"count":0},"num_questions_view":{"count":0},"num_castaways_view":{"count":0},"personas_view":{"questioncaster":[0,0],"lurkcaster":[0.11764705882352941,"4"],"ghostcaster":[0.57,"4",1672056767590.819],"gramcaster":[0,0],"replyguy":[0,0],"shillcaster":[0,0],"threadcastor":[0,0],"botcaster":[0,0],"castaway":[0,0],"cryptocaster":[0,0],"birdappcaster":[0,0]}}}