{"2416":{"user_number_view":{"number":"2416"},"user_card_view":{"avatar_url":"https://lh3.googleusercontent.com/EJ9tam9fAPQfST6imZRC6xeMeohVhT8vDF5l5Dk0UyTosfzlYj3POD5bicSHj1XHvTl5r1SE7juaJFf954M-ocA","display_name":"Will Price","username":"willprice","fid":"2416","bio":"hi"},"num_casts_view":{"count":"2"},"num_likes_view":{"count":"3"},"topics_positive_view":{"entities":[],"counts":[]},"topics_view":{"entities":["farcaster"],"counts":["1"]},"num_liked_by_view":{"count":"18"},"profile_fans_view":{"fans":[{"fid":56,"username":"dcposch","display_name":"dcposch.eth","avatar_url":"https://i.seadn.io/gae/JUbGP1Idb08BeW4f7PQ3hp5PVk8DRCqzlh5ygxHdoSCUWMSNplJxoZBUJkMlPXx7FacPo3V2GA0SwD9NmBzekGejaNpCr9HJ_cwUlZI?w=500&auto=format","count":2},{"fid":785,"username":"vapeape","display_name":"vapeape","avatar_url":"https://lh3.googleusercontent.com/LD5lFXWeCwf0p1OLf5HDKciGAprhUUUnNiz5nrGnyGPdUv6hu0vBOc0qRyPuhWpTjRo9GsXX21bSwjHD4Z6WWTNR","count":2},{"fid":340,"username":"shotbydanni","display_name":"Danny","avatar_url":"https://lh3.googleusercontent.com/5L7DllPujtF_3_ole_2l84bEjyBz6Y6Dg0LxUgmXiXA0ECjOYnjW1RVpPWz_PcG8AogKkkZfdZ3ikUY5NZrTfp5yPJMc2KPHkEvQWQ","count":1},{"fid":474,"username":"pdr","display_name":"Peter Rood","avatar_url":"https://i.seadn.io/gae/F-g4Y0OlaDZmK2m-rzPvN2hX1Vx2seHmxCSFwj7rrysVjcsHeSsNwpInQgg_KOf5MxzEECF6pci87d5JZ2mp1gPjxhCtPQLt6NiILg?w=500&auto=format","count":1},{"fid":576,"username":"nonlinear","display_name":"Jonny Mack","avatar_url":"https://i.seadn.io/gae/oeyOFjLzIVCMec49KdmBp24ZHL82XXqLLDlLRuvUR8InycSpmf9ZtSCfN69lgojeOoucD7fU9cjxAt4raFBTTgSo34gD5lSZ83Klb1k?w=500&auto=format","count":1},{"fid":762,"username":"alvesjtiago","display_name":"Tiago","avatar_url":"https://lh3.googleusercontent.com/ZWj1IEZ7XM_zS61pCbldx4pcfcpKBB3ig6DlMj4jh9Emzq-g2aWK1gTiRbraBNdeht9VFjeyG-GlSmtEh-oirCiH7TZszueWP7oU","count":1},{"fid":961,"username":"evaluate","display_name":"Christian","avatar_url":"https://openseauserdata.com/files/c72d7a956e0e1f579cc37b7149a1651e.svg","count":1},{"fid":1230,"username":"abc","display_name":"abc","avatar_url":"https://lh3.googleusercontent.com/c3WCdzqT5PVKSqzk2813_tjao3VAOA5qvhnYvWS5GwBVHA5nJCMEFzSk7QpsZY3mUvDiRGGt_b1KjO3Pq_DHs-52SjNZJUVcmiI-Gh4","count":1},{"fid":1236,"username":"syed","display_name":"Syed Shah 🏴‍☠️🌊","avatar_url":"https://lh3.googleusercontent.com/4sAqdYpbifMbqK7llU9P0v8tck2oG72W2u5ulNijR8S1yAx2fE-B9HOSvp5xIRky1tkDEESyb6T0f-6ZThovH-Nvpit5ftfnsS8wEjE","count":1},{"fid":1430,"username":"wijuwiju","display_name":"wijuwiju.eth","avatar_url":"https://i.imgur.com/oeyZjsk.jpg","count":1}]},"emojis_view":{"emojis":[]},"top_casts_view":{"top_casts":[{"text":"hello farcaster","thread_hash":"0xa26149a5e8242fda9264d420ae30bd308bd5fbf8e98613b472def2f9cce9b970","hash":"0xa26149a5e8242fda9264d420ae30bd308bd5fbf8e98613b472def2f9cce9b970","likes":16,"replies":3,"recasts":1},{"text":"gm","thread_hash":"0x26152e4a2dbde7fd72c9a8a345be12f46f15a3770f710c5765dc43fae2f2d165","hash":"0x1da74432f3d13aabf363dc828e93f31c1eb28f1e39ece4df4ffcc43a66cd7d3b","likes":2,"replies":0,"recasts":0}]},"first_cast_view":{"cast":{"fid":"2416","text":"hello farcaster","published_at":"2022-09-29T16:00:44.271Z","hash":"0xa26149a5e8242fda9264d420ae30bd308bd5fbf8e98613b472def2f9cce9b970"}},"top_domains_view":{"top_domains":[]},"responded_by_view":{"top_replies":[{"fid":3,"username":"dwr","display_name":"Dan Romero","avatar_url":"https://res.cloudinary.com/merkle-manufactory/image/fetch/c_fill,f_png,w_256/https://lh3.googleusercontent.com/MyUBL0xHzMeBu7DXQAqv0bM9y6s4i4qjnhcXz5fxZKS3gwWgtamxxmxzCJX7m2cuYeGalyseCA2Y6OBKDMR06TWg2uwknnhdkDA1AA","count":1},{"fid":1024,"username":"cdt","display_name":"cdt","avatar_url":"https://i.seadn.io/gae/pbJOBddHL9e0g0rGMr1Mib_1A8LgfzbyjUlHPPMouMX_XsoFTsFJ96ugesejwiMuSTLqShmPlCPDdmzQKkB6dD4FKtGJZsUmJaTy?w=500&auto=format","count":1},{"fid":1236,"username":"syed","display_name":"Syed Shah 🏴‍☠️🌊","avatar_url":"https://lh3.googleusercontent.com/4sAqdYpbifMbqK7llU9P0v8tck2oG72W2u5ulNijR8S1yAx2fE-B9HOSvp5xIRky1tkDEESyb6T0f-6ZThovH-Nvpit5ftfnsS8wEjE","count":1}]},"responded_to_view":{"top_replies":[{"fid":2454,"username":"andy8052","display_name":"andy8052","avatar_url":"https://i.seadn.io/gae/iqPWSegSeSy5nKeMz0Shc7-v56LA5J9lz7jro4S094tKo9zQH2vQ3J_ZAI7__fiMUW2rdTV178NojrQxUhNyyCy3w2r3-xmMMRu2Sw?w=500&auto=format","count":1}]},"num_gms_view":{"count":"3"},"casts_over_time_view":{"data":[{"week":"2022-01-02T23:00:00.000Z","count":"0"},{"week":"2022-01-09T23:00:00.000Z","count":"0"},{"week":"2022-01-16T23:00:00.000Z","count":"0"},{"week":"2022-01-23T23:00:00.000Z","count":"0"},{"week":"2022-01-30T23:00:00.000Z","count":"0"},{"week":"2022-02-06T23:00:00.000Z","count":"0"},{"week":"2022-02-13T23:00:00.000Z","count":"0"},{"week":"2022-02-20T23:00:00.000Z","count":"0"},{"week":"2022-02-27T23:00:00.000Z","count":"0"},{"week":"2022-03-06T23:00:00.000Z","count":"0"},{"week":"2022-03-13T23:00:00.000Z","count":"0"},{"week":"2022-03-20T23:00:00.000Z","count":"0"},{"week":"2022-03-27T22:00:00.000Z","count":"0"},{"week":"2022-04-03T22:00:00.000Z","count":"0"},{"week":"2022-04-10T22:00:00.000Z","count":"0"},{"week":"2022-04-17T22:00:00.000Z","count":"0"},{"week":"2022-04-24T22:00:00.000Z","count":"0"},{"week":"2022-05-01T22:00:00.000Z","count":"0"},{"week":"2022-05-08T22:00:00.000Z","count":"0"},{"week":"2022-05-15T22:00:00.000Z","count":"0"},{"week":"2022-05-22T22:00:00.000Z","count":"0"},{"week":"2022-05-29T22:00:00.000Z","count":"0"},{"week":"2022-06-05T22:00:00.000Z","count":"0"},{"week":"2022-06-12T22:00:00.000Z","count":"0"},{"week":"2022-06-19T22:00:00.000Z","count":"0"},{"week":"2022-06-26T22:00:00.000Z","count":"0"},{"week":"2022-07-03T22:00:00.000Z","count":"0"},{"week":"2022-07-10T22:00:00.000Z","count":"0"},{"week":"2022-07-17T22:00:00.000Z","count":"0"},{"week":"2022-07-24T22:00:00.000Z","count":"0"},{"week":"2022-07-31T22:00:00.000Z","count":"0"},{"week":"2022-08-07T22:00:00.000Z","count":"0"},{"week":"2022-08-14T22:00:00.000Z","count":"0"},{"week":"2022-08-21T22:00:00.000Z","count":"0"},{"week":"2022-08-28T22:00:00.000Z","count":"0"},{"week":"2022-09-04T22:00:00.000Z","count":"0"},{"week":"2022-09-11T22:00:00.000Z","count":"0"},{"week":"2022-09-18T22:00:00.000Z","count":"0"},{"week":"2022-09-25T22:00:00.000Z","count":"2"},{"week":"2022-10-02T22:00:00.000Z","count":"0"},{"week":"2022-10-09T22:00:00.000Z","count":"0"},{"week":"2022-10-16T22:00:00.000Z","count":"0"},{"week":"2022-10-23T22:00:00.000Z","count":"0"},{"week":"2022-10-30T23:00:00.000Z","count":"0"},{"week":"2022-11-06T23:00:00.000Z","count":"0"},{"week":"2022-11-13T23:00:00.000Z","count":"0"},{"week":"2022-11-20T23:00:00.000Z","count":"0"},{"week":"2022-11-27T23:00:00.000Z","count":"0"},{"week":"2022-12-04T23:00:00.000Z","count":"0"},{"week":"2022-12-11T23:00:00.000Z","count":"0"},{"week":"2022-12-18T23:00:00.000Z","count":"0"}],"max":2},"casted_images_view":{"data":[]},"num_threads_view":{"count":0},"num_replies_view":{"count":"1"},"num_questions_view":{"count":0},"num_castaways_view":{"count":0},"personas_view":{"questioncaster":[0,0],"lurkcaster":[0.13043478260869565,"3"],"ghostcaster":[0.68,"3",1672073490086.3328],"gramcaster":[0,0],"replyguy":[0.5,"1"],"shillcaster":[0,0],"threadcastor":[0,0],"botcaster":[0.03125,"1"],"castaway":[0,0],"cryptocaster":[0,0],"birdappcaster":[0,0]}}}