{"4988":{"user_number_view":{"number":"4988"},"user_card_view":{"avatar_url":"https://kobe.show/wp-content/uploads/2022/03/dekobeshow_headermedia-e1647179138561.jpg","display_name":"Kobe.eth","username":"kobe","fid":"4988","bio":"Trying hard to improve my speling."},"num_casts_view":{"count":"4"},"num_likes_view":{"count":"2"},"topics_positive_view":{"entities":["account"],"counts":["1"]},"topics_view":{"entities":["@balajis","@gilles","account","farcaster","hardware wallet","investors","journalist","reddit","web3"],"counts":["1","1","1","1","1","1","1","1","1"]},"num_liked_by_view":{"count":"20"},"profile_fans_view":{"fans":[{"fid":1655,"username":"juan","display_name":"Juan Rivera Perez","avatar_url":"https://i.imgur.com/13ATfIj.jpg","count":2},{"fid":1946,"username":"dragonbanec","display_name":"Dragonbane Creation","avatar_url":"https://i.seadn.io/gae/PVTEgTvNCn205Ipl_aAEZE5BWXU_zTp-Mg7iJDbjnjHWXIzmvzJTHGnKGTukirlWMpcW-eu6U5tUIrg0pFu21EEkVetuCGBo2-l_Ky0?w=500&auto=format","count":2},{"fid":689,"username":"kiyo","display_name":"Kiyo 🥷☕️","avatar_url":"https://lh3.googleusercontent.com/d6aU4ANXiRE3S1NOHTWbAqa0MDKYWsWgY8nJVTC-sSM77ke5B3bbHyAM3NfhBDpzdQUML5R0KRNh8dAk4iSzUen8HFBKa0R1LtUtOg","count":2},{"fid":1230,"username":"abc","display_name":"abc","avatar_url":"https://lh3.googleusercontent.com/c3WCdzqT5PVKSqzk2813_tjao3VAOA5qvhnYvWS5GwBVHA5nJCMEFzSk7QpsZY3mUvDiRGGt_b1KjO3Pq_DHs-52SjNZJUVcmiI-Gh4","count":2},{"fid":882,"username":"gilles","display_name":"gilles","avatar_url":"https://i.seadn.io/gcs/files/027dd35d9631a35dc6f35872fc606131.png?w=500&auto=format","count":1},{"fid":1190,"username":"kencodes","display_name":"kencodes.eth","avatar_url":"https://openseauserdata.com/files/ddc71bbb22faa2be39721a79b4ba5761.svg","count":1},{"fid":2136,"username":"ljw-wavydude","display_name":"LJW_Wavydude","avatar_url":"https://i.seadn.io/gae/-TRoTvbxEPOSE02qDi7PHDukZA-LErV57D2FcIR4obr8S9wcpdfxBON5WeQyddpLfEqJHUCXp-wiol3ry5ysXXN2egeLKLPKWMcpLw?w=500&auto=format","count":1},{"fid":3872,"username":"slowcrypto","display_name":"_slow_crypto","avatar_url":"https://i.imgur.com/RRU7UUA.jpg","count":1},{"fid":3910,"username":"warcmeinstein","display_name":"Marc","avatar_url":"https://openseauserdata.com/files/b25a18d779727ea867a31a0ab7cb7a29.svg","count":1},{"fid":4215,"username":"sa","display_name":"Simon Anderson","avatar_url":"https://i.seadn.io/gae/CdfBZzmDuldkADexx8RHPSoW6JgR5Qr5RLZiepktsCDNH5tNAQXBo-2JYk3eXVkyrZ2a5BbPi870cMS2bfC8R3_clw71w344o0SUDgE?w=500&auto=format","count":1}]},"emojis_view":{"emojis":[]},"top_casts_view":{"top_casts":[{"text":"I'll be publishing an informal argument on crypto taxation, in line with @balajis argumentation that after the internet made everyone a journalist, web3 makes us all investors.","thread_hash":"0xef85ecbe7af5ef4db7d362a8268457a4eb116a8b7b6607f7ee965d595adfd070","hash":"0xef85ecbe7af5ef4db7d362a8268457a4eb116a8b7b6607f7ee965d595adfd070","likes":10,"replies":2,"recasts":2},{"text":"New on Farcaster. Thanks for the referral @gilles.","thread_hash":"0xc35c05629f63387efdf8ea1a959d1f7fa50bf2a0aed5a037c68642f620ebc9c9","hash":"0xc35c05629f63387efdf8ea1a959d1f7fa50bf2a0aed5a037c68642f620ebc9c9","likes":6,"replies":2,"recasts":1},{"text":"My pseudonymous Reddit account has given me access to a vast world of information - which I am eternally grateful for. Such a great resource.","thread_hash":"0x19f9ceab2eed031c613eed940c1663a2c96ce02346cbd4eb1ec3f1097f040178","hash":"0x19f9ceab2eed031c613eed940c1663a2c96ce02346cbd4eb1ec3f1097f040178","likes":4,"replies":0,"recasts":1},{"text":"Should probably write a hardware wallet introduction for people new to the space. So little education still.","thread_hash":"0xc6b8bafcde470b6fe1caf20b002a80134dc06ecc674f3dabb1f0a8e1f8f598ff","hash":"0xc6b8bafcde470b6fe1caf20b002a80134dc06ecc674f3dabb1f0a8e1f8f598ff","likes":0,"replies":0,"recasts":0}]},"first_cast_view":{"cast":{"fid":"4988","text":"New on Farcaster. Thanks for the referral @gilles.","published_at":"2022-11-08T15:06:39.592Z","hash":"0xc35c05629f63387efdf8ea1a959d1f7fa50bf2a0aed5a037c68642f620ebc9c9"}},"top_domains_view":{"top_domains":[]},"responded_by_view":{"top_replies":[{"fid":417,"username":"northchop","display_name":"northchop","avatar_url":"https://i.imgur.com/AONaC8u.jpg","count":1},{"fid":1655,"username":"juan","display_name":"Juan Rivera Perez","avatar_url":"https://i.imgur.com/13ATfIj.jpg","count":1},{"fid":2136,"username":"ljw-wavydude","display_name":"LJW_Wavydude","avatar_url":"https://i.seadn.io/gae/-TRoTvbxEPOSE02qDi7PHDukZA-LErV57D2FcIR4obr8S9wcpdfxBON5WeQyddpLfEqJHUCXp-wiol3ry5ysXXN2egeLKLPKWMcpLw?w=500&auto=format","count":1},{"fid":3872,"username":"slowcrypto","display_name":"_slow_crypto","avatar_url":"https://i.imgur.com/RRU7UUA.jpg","count":1}]},"responded_to_view":{"top_replies":[]},"num_gms_view":{"count":0},"casts_over_time_view":{"data":[{"week":"2022-01-02T23:00:00.000Z","count":"0"},{"week":"2022-01-09T23:00:00.000Z","count":"0"},{"week":"2022-01-16T23:00:00.000Z","count":"0"},{"week":"2022-01-23T23:00:00.000Z","count":"0"},{"week":"2022-01-30T23:00:00.000Z","count":"0"},{"week":"2022-02-06T23:00:00.000Z","count":"0"},{"week":"2022-02-13T23:00:00.000Z","count":"0"},{"week":"2022-02-20T23:00:00.000Z","count":"0"},{"week":"2022-02-27T23:00:00.000Z","count":"0"},{"week":"2022-03-06T23:00:00.000Z","count":"0"},{"week":"2022-03-13T23:00:00.000Z","count":"0"},{"week":"2022-03-20T23:00:00.000Z","count":"0"},{"week":"2022-03-27T22:00:00.000Z","count":"0"},{"week":"2022-04-03T22:00:00.000Z","count":"0"},{"week":"2022-04-10T22:00:00.000Z","count":"0"},{"week":"2022-04-17T22:00:00.000Z","count":"0"},{"week":"2022-04-24T22:00:00.000Z","count":"0"},{"week":"2022-05-01T22:00:00.000Z","count":"0"},{"week":"2022-05-08T22:00:00.000Z","count":"0"},{"week":"2022-05-15T22:00:00.000Z","count":"0"},{"week":"2022-05-22T22:00:00.000Z","count":"0"},{"week":"2022-05-29T22:00:00.000Z","count":"0"},{"week":"2022-06-05T22:00:00.000Z","count":"0"},{"week":"2022-06-12T22:00:00.000Z","count":"0"},{"week":"2022-06-19T22:00:00.000Z","count":"0"},{"week":"2022-06-26T22:00:00.000Z","count":"0"},{"week":"2022-07-03T22:00:00.000Z","count":"0"},{"week":"2022-07-10T22:00:00.000Z","count":"0"},{"week":"2022-07-17T22:00:00.000Z","count":"0"},{"week":"2022-07-24T22:00:00.000Z","count":"0"},{"week":"2022-07-31T22:00:00.000Z","count":"0"},{"week":"2022-08-07T22:00:00.000Z","count":"0"},{"week":"2022-08-14T22:00:00.000Z","count":"0"},{"week":"2022-08-21T22:00:00.000Z","count":"0"},{"week":"2022-08-28T22:00:00.000Z","count":"0"},{"week":"2022-09-04T22:00:00.000Z","count":"0"},{"week":"2022-09-11T22:00:00.000Z","count":"0"},{"week":"2022-09-18T22:00:00.000Z","count":"0"},{"week":"2022-09-25T22:00:00.000Z","count":"0"},{"week":"2022-10-02T22:00:00.000Z","count":"0"},{"week":"2022-10-09T22:00:00.000Z","count":"0"},{"week":"2022-10-16T22:00:00.000Z","count":"0"},{"week":"2022-10-23T22:00:00.000Z","count":"0"},{"week":"2022-10-30T23:00:00.000Z","count":"0"},{"week":"2022-11-06T23:00:00.000Z","count":"3"},{"week":"2022-11-13T23:00:00.000Z","count":"1"},{"week":"2022-11-20T23:00:00.000Z","count":"0"},{"week":"2022-11-27T23:00:00.000Z","count":"0"},{"week":"2022-12-04T23:00:00.000Z","count":"0"},{"week":"2022-12-11T23:00:00.000Z","count":"0"},{"week":"2022-12-18T23:00:00.000Z","count":"0"}],"max":3},"casted_images_view":{"data":[]},"num_threads_view":{"count":0},"num_replies_view":{"count":0},"num_questions_view":{"count":0},"num_castaways_view":{"count":"1"},"personas_view":{"questioncaster":[0,0],"lurkcaster":[0.047619047619047616,"2"],"ghostcaster":[0.76,"2",1672086382530.3704],"gramcaster":[0,0],"replyguy":[0,0],"shillcaster":[0,0],"threadcastor":[0,0],"botcaster":[0,0],"castaway":[0.25,"1"],"cryptocaster":[0,0],"birdappcaster":[0,0]}}}