{"4257":{"user_number_view":{"number":"4257"},"user_card_view":{"avatar_url":"https://lh3.googleusercontent.com/IPzIu4xHfibQGF1NTfG0t5oYg6-xbS8hL23SD2pgNBnLzrVx2Wo5u4I7IHdA-z0VUR1fZLzMNs78QEivqXLhXmuLnjtZbmAfTIuisy4","display_name":"Dr. Cinjon","username":"cinjon","fid":"4257","bio":null},"num_casts_view":{"count":"4"},"num_likes_view":{"count":"2"},"topics_positive_view":{"entities":[],"counts":[]},"topics_view":{"entities":["0x","frax","https://cinjon.com/systems-0x-analysis","https://cinjon.com/systems-0x-synthesis","https://cinjon.com/systems-frax-analysis","https://cinjon.com/systems-frax-synthesis","https://twitter.com/cinjoncin/status/1593012483815768064?s=20&t=smylwyqxxydtx3xrrgelew","part","posts","twitter"],"counts":["1","1","1","1","1","1","1","1","1","1"]},"num_liked_by_view":{"count":"6"},"profile_fans_view":{"fans":[{"fid":129,"username":"phil","display_name":"phil","avatar_url":"https://i.seadn.io/gae/V0OzwojGHgQCB0BqJ-RkhmwFLuD847O-4lZ233f8zTlxbn-sWTI03Ue-RbB2tLlnRcNnB910AHGxZuxtISi5pRLsNIX1yU71E31p?w=500&auto=format","count":1},{"fid":1010,"username":"harper","display_name":"Harper Reed","avatar_url":"https://lh3.googleusercontent.com/6idLGu3FdVLwWq9PFHEb4RIDDmfbdGvLUyb8_LhQLEtlgga5HC4AfniHg11uBe2xZcCBmGYiAFM3jUIyZaI5F-4pbcE2fNXqsgLjqg","count":1},{"fid":1432,"username":"eddieosh","display_name":"Ed O'Shaughnessy","avatar_url":"https://i.imgur.com/vHju0nJ.jpg","count":1},{"fid":3279,"username":"stbaasch","display_name":"Stephan Baasch","avatar_url":"https://i.imgur.com/NbaR4yP.jpg","count":1},{"fid":4243,"username":"jonruth","display_name":"Jon (☀️,⚡)","avatar_url":"https://bafybeid44w7bakkehl7tyfaqjwhr3rmsne4clhj56lldmb5n7sqcvpy5pe.ipfs.w3s.link/ipfs/bafybeid44w7bakkehl7tyfaqjwhr3rmsne4clhj56lldmb5n7sqcvpy5pe/JonPFP.png","count":1},{"fid":4257,"username":"cinjon","display_name":"Dr. Cinjon","avatar_url":"https://lh3.googleusercontent.com/IPzIu4xHfibQGF1NTfG0t5oYg6-xbS8hL23SD2pgNBnLzrVx2Wo5u4I7IHdA-z0VUR1fZLzMNs78QEivqXLhXmuLnjtZbmAfTIuisy4","count":1}]},"emojis_view":{"emojis":[]},"top_casts_view":{"top_casts":[{"text":"I spent part of this year applying systems understanding to Web3, beginning with 0x. The result were these posts: https://cinjon.com/systems-0x-analysis, https://cinjon.com/systems-0x-synthesis.","thread_hash":"0x564912f061d1a0b465786270049cd43f131aa1ef22b29a4c5316a89ca8d2855b","hash":"0x564912f061d1a0b465786270049cd43f131aa1ef22b29a4c5316a89ca8d2855b","likes":4,"replies":0,"recasts":1},{"text":"Cross posting my Analysis + Synthesis on Frax here from twitter  https://twitter.com/cinjoncin/status/1593012483815768064?s=20&t=smylWYQxXYdtx3XrrGelew ... https://cinjon.com/systems-frax-synthesis and https://cinjon.com/systems-frax-analysis.","thread_hash":"0x99a2eb87aa96005dae3ee0124909370749b93168ecf76b72d332ca0272e62c0c","hash":"0x99a2eb87aa96005dae3ee0124909370749b93168ecf76b72d332ca0272e62c0c","likes":1,"replies":0,"recasts":0},{"text":"hot take.","thread_hash":"0xb40697755acde3678d8a1165d0a25a33ab085fa63bdff29a5d9cbbf5887983fc","hash":"0x4b5d39112c9efb366adb2530d857d746de71a103a3d896f6ad54818e3d8e4742","likes":1,"replies":0,"recasts":0}]},"first_cast_view":{"cast":{"fid":"4257","text":"I spent part of this year applying systems understanding to Web3, beginning with 0x. The result were these posts: https://cinjon.com/systems-0x-analysis, https://cinjon.com/systems-0x-synthesis.","published_at":"2022-10-25T20:34:25.356Z","hash":"0x564912f061d1a0b465786270049cd43f131aa1ef22b29a4c5316a89ca8d2855b"}},"top_domains_view":{"top_domains":[{"domain":"cinjon.com","count":4},{"domain":"twitter.com","count":1}]},"responded_by_view":{"top_replies":[]},"responded_to_view":{"top_replies":[{"fid":127,"username":"neuroswish","display_name":"Kiran","avatar_url":"https://pbs.twimg.com/profile_images/1572434339790557185/pGy6n8b4_400x400.jpg","count":1}]},"num_gms_view":{"count":0},"casts_over_time_view":{"data":[{"week":"2022-01-02T23:00:00.000Z","count":"0"},{"week":"2022-01-09T23:00:00.000Z","count":"0"},{"week":"2022-01-16T23:00:00.000Z","count":"0"},{"week":"2022-01-23T23:00:00.000Z","count":"0"},{"week":"2022-01-30T23:00:00.000Z","count":"0"},{"week":"2022-02-06T23:00:00.000Z","count":"0"},{"week":"2022-02-13T23:00:00.000Z","count":"0"},{"week":"2022-02-20T23:00:00.000Z","count":"0"},{"week":"2022-02-27T23:00:00.000Z","count":"0"},{"week":"2022-03-06T23:00:00.000Z","count":"0"},{"week":"2022-03-13T23:00:00.000Z","count":"0"},{"week":"2022-03-20T23:00:00.000Z","count":"0"},{"week":"2022-03-27T22:00:00.000Z","count":"0"},{"week":"2022-04-03T22:00:00.000Z","count":"0"},{"week":"2022-04-10T22:00:00.000Z","count":"0"},{"week":"2022-04-17T22:00:00.000Z","count":"0"},{"week":"2022-04-24T22:00:00.000Z","count":"0"},{"week":"2022-05-01T22:00:00.000Z","count":"0"},{"week":"2022-05-08T22:00:00.000Z","count":"0"},{"week":"2022-05-15T22:00:00.000Z","count":"0"},{"week":"2022-05-22T22:00:00.000Z","count":"0"},{"week":"2022-05-29T22:00:00.000Z","count":"0"},{"week":"2022-06-05T22:00:00.000Z","count":"0"},{"week":"2022-06-12T22:00:00.000Z","count":"0"},{"week":"2022-06-19T22:00:00.000Z","count":"0"},{"week":"2022-06-26T22:00:00.000Z","count":"0"},{"week":"2022-07-03T22:00:00.000Z","count":"0"},{"week":"2022-07-10T22:00:00.000Z","count":"0"},{"week":"2022-07-17T22:00:00.000Z","count":"0"},{"week":"2022-07-24T22:00:00.000Z","count":"0"},{"week":"2022-07-31T22:00:00.000Z","count":"0"},{"week":"2022-08-07T22:00:00.000Z","count":"0"},{"week":"2022-08-14T22:00:00.000Z","count":"0"},{"week":"2022-08-21T22:00:00.000Z","count":"0"},{"week":"2022-08-28T22:00:00.000Z","count":"0"},{"week":"2022-09-04T22:00:00.000Z","count":"0"},{"week":"2022-09-11T22:00:00.000Z","count":"0"},{"week":"2022-09-18T22:00:00.000Z","count":"0"},{"week":"2022-09-25T22:00:00.000Z","count":"0"},{"week":"2022-10-02T22:00:00.000Z","count":"0"},{"week":"2022-10-09T22:00:00.000Z","count":"0"},{"week":"2022-10-16T22:00:00.000Z","count":"0"},{"week":"2022-10-23T22:00:00.000Z","count":"2"},{"week":"2022-10-30T23:00:00.000Z","count":"0"},{"week":"2022-11-06T23:00:00.000Z","count":"0"},{"week":"2022-11-13T23:00:00.000Z","count":"2"},{"week":"2022-11-20T23:00:00.000Z","count":"0"},{"week":"2022-11-27T23:00:00.000Z","count":"0"},{"week":"2022-12-04T23:00:00.000Z","count":"0"},{"week":"2022-12-11T23:00:00.000Z","count":"0"},{"week":"2022-12-18T23:00:00.000Z","count":"0"}],"max":2},"casted_images_view":{"data":[]},"num_threads_view":{"count":0},"num_replies_view":{"count":"1"},"num_questions_view":{"count":0},"num_castaways_view":{"count":0},"personas_view":{"questioncaster":[0,0],"lurkcaster":[0.047619047619047616,"2"],"ghostcaster":[0.76,"2",1672082682444.1428],"gramcaster":[0,0],"replyguy":[0.25,"1"],"shillcaster":[0,0],"threadcastor":[0,0],"botcaster":[0.041666666666666664,"1"],"castaway":[0,0],"cryptocaster":[0,0],"birdappcaster":[0.25,1]}}}