{"5385":{"user_number_view":{"number":"5385"},"user_card_view":{"avatar_url":"https://i.seadn.io/gae/BiXct9qSdHl7KOz993drXMUQHT9RxZmUm0AfKyZuUsFBBLzR9LWy_rBvv01ifTA_8TW71RwzgzSIEx8bWyUnoQe8lOD5sqKG6H1wrg?w=500&auto=format","display_name":"Daniel Molina","username":"dmolina","fid":"5385","bio":"Crypto enthusiast. Developer & entrepreneur."},"num_casts_view":{"count":"4"},"num_likes_view":{"count":"3"},"topics_positive_view":{"entities":["modules","team"],"counts":["1","1"]},"topics_view":{"entities":["te","contracts","fundamentals","https://consensys.net/diligence/resources/security-tooling-guide/","https://tokenengineering.net/user/6345e758fa6753c1f902306e/","modules","consensys","team"],"counts":["2","1","1","1","1","1","1","1","1"]},"num_liked_by_view":{"count":"14"},"profile_fans_view":{"fans":[{"fid":1230,"username":"abc","display_name":"abc","avatar_url":"https://lh3.googleusercontent.com/c3WCdzqT5PVKSqzk2813_tjao3VAOA5qvhnYvWS5GwBVHA5nJCMEFzSk7QpsZY3mUvDiRGGt_b1KjO3Pq_DHs-52SjNZJUVcmiI-Gh4","count":2},{"fid":758,"username":"ddd4","display_name":"DDD4","avatar_url":"https://lh3.googleusercontent.com/MWP8EcGVhfG26vG-WjOjy4VwXZwmVPOuZNQ2xBSXrVzwFcLzHR-AkxN2ASz3tv8qLjyP-yePannB6Xrlj7fML7p6fO7wY2hNyvaM5Q","count":1},{"fid":762,"username":"alvesjtiago","display_name":"Tiago","avatar_url":"https://lh3.googleusercontent.com/ZWj1IEZ7XM_zS61pCbldx4pcfcpKBB3ig6DlMj4jh9Emzq-g2aWK1gTiRbraBNdeht9VFjeyG-GlSmtEh-oirCiH7TZszueWP7oU","count":1},{"fid":1214,"username":"df","display_name":"David Furlong","avatar_url":"https://lh3.googleusercontent.com/-S5cdhOpZtJ_Qzg9iPWELEsRTkIsZ7qGYmVlwEORgFB00WWAtZGefRnS4Bjcz5ah40WVOOWeYfU5pP9Eekikb3cLMW2mZQOMQHlWhg","count":1},{"fid":1484,"username":"zico","display_name":"zico","avatar_url":"https://i.seadn.io/gae/yt_mgLOcYF0lGrjbYg5CuCyezH4m12f0KqdOLPU_xEBPFu3WqrDcSBFZpMpO4U94qnyc_cX3K-wq0Pui6PHjgc5B9NrbVZmLa49WTr8?w=500&auto=format","count":1},{"fid":1655,"username":"juan","display_name":"Juan Rivera Perez","avatar_url":"https://i.imgur.com/13ATfIj.jpg","count":1},{"fid":1946,"username":"dragonbanec","display_name":"Dragonbane Creation","avatar_url":"https://i.seadn.io/gae/PVTEgTvNCn205Ipl_aAEZE5BWXU_zTp-Mg7iJDbjnjHWXIzmvzJTHGnKGTukirlWMpcW-eu6U5tUIrg0pFu21EEkVetuCGBo2-l_Ky0?w=500&auto=format","count":1},{"fid":3370,"username":"anku","display_name":"anku","avatar_url":"https://i.imgur.com/jrAy3no.jpg","count":1},{"fid":5303,"username":"yuuki","display_name":"zkYuki","avatar_url":"https://i.imgur.com/RRwX61D.jpg","count":1},{"fid":5329,"username":"volodymyr","display_name":"Volodymyr","avatar_url":"https://i.seadn.io/gae/rnelnNzGbSdaKCVw3u0rbq1KV38ghygrF8fOLjAlBe-Qhg0mfOTmfyD7feqa3ND9K7qNovzmDFHncp_XofPR2H2ZMaTGEvoVE-6ISg?w=500&auto=format","count":1}]},"emojis_view":{"emojis":[]},"top_casts_view":{"top_casts":[{"text":"gm!","thread_hash":"0xa115f302d9ae1d60be19b3f6cd164d71a8dceadde5aae4d1d40c5ff0d9c03cec","hash":"0xa115f302d9ae1d60be19b3f6cd164d71a8dceadde5aae4d1d40c5ff0d9c03cec","likes":9,"replies":1,"recasts":1},{"text":"A good guide to keep up to date about security tools in smart contracts by ConsenSys:\n\nhttps://consensys.net/diligence/resources/security-tooling-guide/","thread_hash":"0x58b2affd88b9e8b9a9fc72ffc6538985811eb439ba2ade5df7523ac32720a250","hash":"0x58b2affd88b9e8b9a9fc72ffc6538985811eb439ba2ade5df7523ac32720a250","likes":3,"replies":0,"recasts":1},{"text":"I just minted the 5 TE Fundamentals course NFTs! I fully recommend the modules. Thank you to all the TE team! \n\nhttps://tokenengineering.net/user/6345e758fa6753c1f902306e/","thread_hash":"0xab216c482c062f33d35b5653ae7098cbddcc4b366d6115ac5ff4242d185fdb8a","hash":"0xab216c482c062f33d35b5653ae7098cbddcc4b366d6115ac5ff4242d185fdb8a","likes":1,"replies":0,"recasts":0}]},"first_cast_view":{"cast":{"fid":"5385","text":"gm!","published_at":"2022-11-16T07:53:47.478Z","hash":"0xa115f302d9ae1d60be19b3f6cd164d71a8dceadde5aae4d1d40c5ff0d9c03cec"}},"top_domains_view":{"top_domains":[{"domain":"consensys.net","count":1},{"domain":"tokenengineering.net","count":1}]},"responded_by_view":{"top_replies":[{"fid":1655,"username":"juan","display_name":"Juan Rivera Perez","avatar_url":"https://i.imgur.com/13ATfIj.jpg","count":1}]},"responded_to_view":{"top_replies":[]},"num_gms_view":{"count":"1"},"casts_over_time_view":{"data":[{"week":"2022-01-02T23:00:00.000Z","count":"0"},{"week":"2022-01-09T23:00:00.000Z","count":"0"},{"week":"2022-01-16T23:00:00.000Z","count":"0"},{"week":"2022-01-23T23:00:00.000Z","count":"0"},{"week":"2022-01-30T23:00:00.000Z","count":"0"},{"week":"2022-02-06T23:00:00.000Z","count":"0"},{"week":"2022-02-13T23:00:00.000Z","count":"0"},{"week":"2022-02-20T23:00:00.000Z","count":"0"},{"week":"2022-02-27T23:00:00.000Z","count":"0"},{"week":"2022-03-06T23:00:00.000Z","count":"0"},{"week":"2022-03-13T23:00:00.000Z","count":"0"},{"week":"2022-03-20T23:00:00.000Z","count":"0"},{"week":"2022-03-27T22:00:00.000Z","count":"0"},{"week":"2022-04-03T22:00:00.000Z","count":"0"},{"week":"2022-04-10T22:00:00.000Z","count":"0"},{"week":"2022-04-17T22:00:00.000Z","count":"0"},{"week":"2022-04-24T22:00:00.000Z","count":"0"},{"week":"2022-05-01T22:00:00.000Z","count":"0"},{"week":"2022-05-08T22:00:00.000Z","count":"0"},{"week":"2022-05-15T22:00:00.000Z","count":"0"},{"week":"2022-05-22T22:00:00.000Z","count":"0"},{"week":"2022-05-29T22:00:00.000Z","count":"0"},{"week":"2022-06-05T22:00:00.000Z","count":"0"},{"week":"2022-06-12T22:00:00.000Z","count":"0"},{"week":"2022-06-19T22:00:00.000Z","count":"0"},{"week":"2022-06-26T22:00:00.000Z","count":"0"},{"week":"2022-07-03T22:00:00.000Z","count":"0"},{"week":"2022-07-10T22:00:00.000Z","count":"0"},{"week":"2022-07-17T22:00:00.000Z","count":"0"},{"week":"2022-07-24T22:00:00.000Z","count":"0"},{"week":"2022-07-31T22:00:00.000Z","count":"0"},{"week":"2022-08-07T22:00:00.000Z","count":"0"},{"week":"2022-08-14T22:00:00.000Z","count":"0"},{"week":"2022-08-21T22:00:00.000Z","count":"0"},{"week":"2022-08-28T22:00:00.000Z","count":"0"},{"week":"2022-09-04T22:00:00.000Z","count":"0"},{"week":"2022-09-11T22:00:00.000Z","count":"0"},{"week":"2022-09-18T22:00:00.000Z","count":"0"},{"week":"2022-09-25T22:00:00.000Z","count":"0"},{"week":"2022-10-02T22:00:00.000Z","count":"0"},{"week":"2022-10-09T22:00:00.000Z","count":"0"},{"week":"2022-10-16T22:00:00.000Z","count":"0"},{"week":"2022-10-23T22:00:00.000Z","count":"0"},{"week":"2022-10-30T23:00:00.000Z","count":"0"},{"week":"2022-11-06T23:00:00.000Z","count":"0"},{"week":"2022-11-13T23:00:00.000Z","count":"2"},{"week":"2022-11-20T23:00:00.000Z","count":"1"},{"week":"2022-11-27T23:00:00.000Z","count":"1"},{"week":"2022-12-04T23:00:00.000Z","count":"0"},{"week":"2022-12-11T23:00:00.000Z","count":"0"},{"week":"2022-12-18T23:00:00.000Z","count":"0"}],"max":2},"casted_images_view":{"data":[]},"num_threads_view":{"count":0},"num_replies_view":{"count":0},"num_questions_view":{"count":0},"num_castaways_view":{"count":0},"personas_view":{"questioncaster":[0,0],"lurkcaster":[0.06976744186046512,"3"],"ghostcaster":[0.66,"3",1672088400128.671],"gramcaster":[0,0],"replyguy":[0,0],"shillcaster":[0,0],"threadcastor":[0,0],"botcaster":[0,0],"castaway":[0,0],"cryptocaster":[0,0],"birdappcaster":[0,0]}}}