{"1316":{"user_number_view":{"number":"1316"},"user_card_view":{"avatar_url":"https://lh3.googleusercontent.com/QV4WlrDahIHpFFQwtUy-HaDt8jbNJyTJk2B-eO4XH_GbFKGZq1P5-dNalvV5JoohUl_JdPfZtGe6s67OSBS7FLMKzzmzzgfQKU0a","display_name":"Gio","username":"gio","fid":"1316","bio":"Blockchain and software engineer at Duke University. Interested in security, applied SNARKs, account abstraction and consensus algorithms."},"num_casts_view":{"count":"2"},"num_likes_view":{"count":"2"},"topics_positive_view":{"entities":[],"counts":[]},"topics_view":{"entities":["@farcaster","builders","content"],"counts":["1","1","1"]},"num_liked_by_view":{"count":"0"},"profile_fans_view":{"fans":[]},"emojis_view":{"emojis":[]},"top_casts_view":{"top_casts":[{"text":"I need to start using @farcaster more. If anyone has tips for creating content, please drop them below!","thread_hash":"0xd415907e7af72a0f264682db0fc49c3edc10c4b5b6cba860cefbe91db08fe99f","hash":"0xd415907e7af72a0f264682db0fc49c3edc10c4b5b6cba860cefbe91db08fe99f","likes":0,"replies":0,"recasts":0},{"text":"This was a great post. Thank you for providing guidance to builders in the space!","thread_hash":"0xc97c722d877b00897b3895ea7eb76bdc3a7bad298a88649ccf00850464a3dc30","hash":"0x3143d145da7243f7f9888c0f35bcd96c51b38e7621f7a81a9d41154167a8e869","likes":0,"replies":0,"recasts":0}]},"first_cast_view":{"cast":{"fid":"1316","text":"I need to start using @farcaster more. If anyone has tips for creating content, please drop them below!","published_at":"2022-12-09T18:43:50.405Z","hash":"0xd415907e7af72a0f264682db0fc49c3edc10c4b5b6cba860cefbe91db08fe99f"}},"top_domains_view":{"top_domains":[]},"responded_by_view":{"top_replies":[]},"responded_to_view":{"top_replies":[{"fid":5650,"username":"vbuterin","display_name":"Vitalik Buterin","avatar_url":"https://i.imgur.com/gF9Yaeg.jpg","count":1}]},"num_gms_view":{"count":0},"casts_over_time_view":{"data":[{"week":"2022-01-02T23:00:00.000Z","count":"0"},{"week":"2022-01-09T23:00:00.000Z","count":"0"},{"week":"2022-01-16T23:00:00.000Z","count":"0"},{"week":"2022-01-23T23:00:00.000Z","count":"0"},{"week":"2022-01-30T23:00:00.000Z","count":"0"},{"week":"2022-02-06T23:00:00.000Z","count":"0"},{"week":"2022-02-13T23:00:00.000Z","count":"0"},{"week":"2022-02-20T23:00:00.000Z","count":"0"},{"week":"2022-02-27T23:00:00.000Z","count":"0"},{"week":"2022-03-06T23:00:00.000Z","count":"0"},{"week":"2022-03-13T23:00:00.000Z","count":"0"},{"week":"2022-03-20T23:00:00.000Z","count":"0"},{"week":"2022-03-27T22:00:00.000Z","count":"0"},{"week":"2022-04-03T22:00:00.000Z","count":"0"},{"week":"2022-04-10T22:00:00.000Z","count":"0"},{"week":"2022-04-17T22:00:00.000Z","count":"0"},{"week":"2022-04-24T22:00:00.000Z","count":"0"},{"week":"2022-05-01T22:00:00.000Z","count":"0"},{"week":"2022-05-08T22:00:00.000Z","count":"0"},{"week":"2022-05-15T22:00:00.000Z","count":"0"},{"week":"2022-05-22T22:00:00.000Z","count":"0"},{"week":"2022-05-29T22:00:00.000Z","count":"0"},{"week":"2022-06-05T22:00:00.000Z","count":"0"},{"week":"2022-06-12T22:00:00.000Z","count":"0"},{"week":"2022-06-19T22:00:00.000Z","count":"0"},{"week":"2022-06-26T22:00:00.000Z","count":"0"},{"week":"2022-07-03T22:00:00.000Z","count":"0"},{"week":"2022-07-10T22:00:00.000Z","count":"0"},{"week":"2022-07-17T22:00:00.000Z","count":"0"},{"week":"2022-07-24T22:00:00.000Z","count":"0"},{"week":"2022-07-31T22:00:00.000Z","count":"0"},{"week":"2022-08-07T22:00:00.000Z","count":"0"},{"week":"2022-08-14T22:00:00.000Z","count":"0"},{"week":"2022-08-21T22:00:00.000Z","count":"0"},{"week":"2022-08-28T22:00:00.000Z","count":"0"},{"week":"2022-09-04T22:00:00.000Z","count":"0"},{"week":"2022-09-11T22:00:00.000Z","count":"0"},{"week":"2022-09-18T22:00:00.000Z","count":"0"},{"week":"2022-09-25T22:00:00.000Z","count":"0"},{"week":"2022-10-02T22:00:00.000Z","count":"0"},{"week":"2022-10-09T22:00:00.000Z","count":"0"},{"week":"2022-10-16T22:00:00.000Z","count":"0"},{"week":"2022-10-23T22:00:00.000Z","count":"0"},{"week":"2022-10-30T23:00:00.000Z","count":"0"},{"week":"2022-11-06T23:00:00.000Z","count":"0"},{"week":"2022-11-13T23:00:00.000Z","count":"0"},{"week":"2022-11-20T23:00:00.000Z","count":"0"},{"week":"2022-11-27T23:00:00.000Z","count":"0"},{"week":"2022-12-04T23:00:00.000Z","count":"2"},{"week":"2022-12-11T23:00:00.000Z","count":"0"},{"week":"2022-12-18T23:00:00.000Z","count":"0"}],"max":2},"casted_images_view":{"data":[]},"num_threads_view":{"count":0},"num_replies_view":{"count":"1"},"num_questions_view":{"count":0},"num_castaways_view":{"count":"1"},"personas_view":{"questioncaster":[0,0],"lurkcaster":[0.09090909090909091,"2"],"ghostcaster":[0.78,"2",1672068793838.2195],"gramcaster":[0,0],"replyguy":[0.5,"1"],"shillcaster":[0,0],"threadcastor":[0,0],"botcaster":[0.045454545454545456,"1"],"castaway":[1,"1"],"cryptocaster":[0,0],"birdappcaster":[0,0]}}}